typora_cos/__init__.py
typora_cos/config.xml
typora_cos/qcloud.py
typora_cos/factory/ClientFactory.py
typora_cos/factory/ConfigFactory.py
typora_cos/factory/__init__.py
typora_cos/resource/FileSystemResource.py
typora_cos/resource/ResourceLoader.py
typora_cos/resource/UrlResource.py
typora_cos/resource/__init__.py
typora_cos/service/CosClient.py
typora_cos/service/CosFile.py
typora_cos/service/__init__.py
typora_cos-2.0.2.dist-info/LICENSE
typora_cos-2.0.2.dist-info/METADATA
typora_cos-2.0.2.dist-info/WHEEL
typora_cos-2.0.2.dist-info/top_level.txt
typora_cos-2.0.2.dist-info/RECORD
