Metadata-Version: 2.1
Name: typora-cos
Version: 2.0.2
Summary: tool for uploading typora images to qcloud cos
Home-page: https://gitee.com/liaozb1996/typroa_qcloud_cos.git
Author: liaozibo
Author-email: liaozibo@qq.com
License: UNKNOWN
Platform: UNKNOWN
Classifier: Programming Language :: Python :: 3
Classifier: License :: OSI Approved :: GNU General Public License v3 (GPLv3)
Classifier: Operating System :: OS Independent
Requires-Python: >=3.6
Requires-Dist: cos-python-sdk-v5
Requires-Dist: requests
Requires-Dist: Pillow
